Approximation/__init__.py
Approximation/lognormalAproximations.py
Approximation/normalSummation.py
Approximation/validation.py
Approximation-1.0.2.dist-info/METADATA
Approximation-1.0.2.dist-info/WHEEL
Approximation-1.0.2.dist-info/top_level.txt
Approximation-1.0.2.dist-info/RECORD
