Metadata-Version: 2.1
Name: Approximation
Version: 1.0.2
Summary: This package is created to approximate distributions
Author: Taha Huzeyfe Aktas
Author-email: taha.huzeyfe@gmail.com
Classifier: Programming Language :: Python :: 3
Classifier: License :: OSI Approved :: MIT License
Classifier: Operating System :: OS Independent
Requires-Dist: scipy
